{
    "general": [
        {
            "id": "gen0",
            "message": "Hmm, this doesn't seem right. Please do not use integer IDs for creating a new account. This is just bad practice."
        }
    ],
    "users": [
        {
            "id": "usr0",
            "message": "User was not found."
        },
        {
            "id": "usr1",
            "message": "Password cannot be empty."
        },
        {
            "id": "usr2",
            "message": "User password was not correct."
        },
        {
            "id": "usr3",
            "message": "Could not delete this priviledged user: at least one is needed."
        },
        {
            "id": "usr4",
            "message": "Invalid username or password."
        },
        {
            "id": "usr5",
            "message": "Authentication is required. Please login."
        },
        {
            "id": "usr6",
            "message": "Authentication as a priviledged user is required."
        }
    ],
    "registration": [
        {
            "id": "reg0",
            "message": "Login ID and password have to be entered."
        },
        {
            "id": "reg1",
            "message": "Login ID is already taken or is reserved."
        },
        {
            "id": "reg2",
            "message": "Login ID contains invalid characters."
        },
        {
            "id": "reg3",
            "message": "Login ID is too short."
        },
        {
            "id": "reg4",
            "message": "Password must be input."
        },
        {
            "id": "reg5",
            "message": "Password is too short."
        },
        {
            "id": "reg6",
            "message": "The password and password confirmation do not match."
        },
        {
            "id": "reg7",
            "message": "The email address is not valid."
        }
    ]
}